captioneditor/__init__.py
captioneditor/editor.py
captioneditor-0.1.8.dist-info/LICENSE
captioneditor-0.1.8.dist-info/METADATA
captioneditor-0.1.8.dist-info/WHEEL
captioneditor-0.1.8.dist-info/entry_points.txt
captioneditor-0.1.8.dist-info/top_level.txt
captioneditor-0.1.8.dist-info/RECORD
