Metadata-Version: 2.1
Name: captioneditor
Version: 0.1.8
Summary: A tool to replace words and phrases in a caption file with new words or phrases, offset each caption by a specified amount, and cut off captions after a specified time.
Author-email: Henry Speaker <HenrySpeaker24@gmail.com>
Project-URL: Source, https://github.com/HenrySpeaker/CaptionEditor
Classifier: Programming Language :: Python :: 3
Classifier: License :: OSI Approved :: MIT License
Classifier: Operating System :: OS Independent
Requires-Python: >=3.10
License-File: LICENSE
Requires-Dist: coverage
Requires-Dist: flashtext2
Requires-Dist: pytest
Requires-Dist: setuptools
Requires-Dist: webvtt-py
Requires-Dist: pycaption
Requires-Dist: xmldiff
